eoapi_cdk/__init__.py
eoapi_cdk/py.typed
eoapi_cdk/_jsii/__init__.py
eoapi_cdk/_jsii/eoapi-cdk@11.1.0.jsii.tgz
eoapi_cdk-11.1.0.dist-info/LICENSE
eoapi_cdk-11.1.0.dist-info/METADATA
eoapi_cdk-11.1.0.dist-info/WHEEL
eoapi_cdk-11.1.0.dist-info/top_level.txt
eoapi_cdk-11.1.0.dist-info/RECORD
