Metadata-Version: 2.1
Name: eoapi-cdk
Version: 11.1.0
Summary: A set of constructs deploying pgSTAC with CDK
Home-page: https://github.com/developmentseed/eoapi-cdk.git
Author: Anthony Lukach<anthony@developmentseed.org>
License: ISC
Project-URL: Source, https://github.com/developmentseed/eoapi-cdk.git
Classifier: Intended Audience :: Developers
Classifier: Operating System :: OS Independent
Classifier: Programming Language :: JavaScript
Classifier: Programming Language :: Python :: 3 :: Only
Classifier: Programming Language :: Python :: 3.9
Classifier: Programming Language :: Python :: 3.10
Classifier: Programming Language :: Python :: 3.11
Classifier: Typing :: Typed
Classifier: Development Status :: 4 - Beta
Classifier: License :: OSI Approved
Requires-Python: ~=3.9
License-File: LICENSE
Requires-Dist: aws-cdk-lib <3.0.0,>=2.220.0
Requires-Dist: constructs <11.0.0,>=10.4.2
Requires-Dist: jsii <2.0.0,>=1.117.0
Requires-Dist: publication >=0.0.3
Requires-Dist: typeguard <4.3.0,>=2.13.3
